weather_serv.py
muxue_mcp-0.1.0.dist-info/METADATA
muxue_mcp-0.1.0.dist-info/WHEEL
muxue_mcp-0.1.0.dist-info/top_level.txt
muxue_mcp-0.1.0.dist-info/RECORD
