Metadata-Version: 2.4
Name: muxue-mcp
Version: 0.1.0
Summary: 天气查询mcp server
Requires-Python: >=3.13
Requires-Dist: httpx>=0.28.1
Requires-Dist: mcp[cli]>=1.9.0
